pyastgrep/__init__.py
pyastgrep/api.py
pyastgrep/ast_utils.py
pyastgrep/asts.py
pyastgrep/cli.py
pyastgrep/color.py
pyastgrep/context.py
pyastgrep/dump.py
pyastgrep/files.py
pyastgrep/ignores.py
pyastgrep/printer.py
pyastgrep/py.typed
pyastgrep/search.py
pyastgrep/xml.py
pyastgrep/xpath2.py
pyastgrep-1.6.dist-info/METADATA
pyastgrep-1.6.dist-info/WHEEL
pyastgrep-1.6.dist-info/entry_points.txt
pyastgrep-1.6.dist-info/top_level.txt
pyastgrep-1.6.dist-info/RECORD
