Metadata-Version: 2.4
Name: pyastgrep
Version: 1.6
Summary: A search/query tool for Python abstract syntax trees
Author: Luke Plant
License: MIT
Project-URL: Homepage, https://github.com/spookylukey/pyastgrep
Keywords: xpath xml ast asts syntax query css grep
Classifier: Development Status :: 4 - Beta
Classifier: Programming Language :: Python
Classifier: Programming Language :: Python :: 3
Classifier: Programming Language :: Python :: 3.9
Classifier: Programming Language :: Python :: 3.10
Classifier: Programming Language :: Python :: 3.11
Classifier: Programming Language :: Python :: 3.12
Classifier: Programming Language :: Python :: 3.13
Classifier: Intended Audience :: Developers
Classifier: Operating System :: OS Independent
Classifier: License :: OSI Approved :: MIT License
Classifier: Natural Language :: English
Requires-Python: >=3.9
Requires-Dist: lxml>=3.3.5
Requires-Dist: elementpath
Requires-Dist: astpretty
Requires-Dist: pathspec
Requires-Dist: cssselect>=1.2
Requires-Dist: backports.strenum; python_version < "3.11"
Requires-Dist: typing-extensions>=4.12.2
